poseidon_cli/__init__.py
poseidon_cli/__main__.py
poseidon_cli/cli.py
poseidon_cli/commands.py
poseidon_cli-0.18.2.dist-info/entry_points.txt
poseidon_cli-0.18.2.dist-info/WHEEL
poseidon_cli-0.18.2.dist-info/METADATA
poseidon_cli-0.18.2.dist-info/RECORD
