Metadata-Version: 2.1
Name: poseidon-cli
Version: 0.18.2
Summary: Commandline tool for querying Poseidon via Prometheus
License: Apache-2.0
Author: cglewis
Author-email: clewis@iqt.org
Requires-Python: >=3.8,<3.11
Classifier: License :: OSI Approved :: Apache Software License
Classifier: Programming Language :: Python :: 3
Classifier: Programming Language :: Python :: 3.8
Classifier: Programming Language :: Python :: 3.9
Classifier: Programming Language :: Python :: 3.10
Requires-Dist: cmd2 (==2.4.2)
Requires-Dist: natural (==0.2.0)
Requires-Dist: poseidon-core (==0.18.1)
Requires-Dist: texttable (==1.6.4)
Project-URL: homepage, https://github.com/IQTLabs/poseidon
